ci_test/__init__.py
ci_test/__main__.py
ci_test/cli.py
ci_test/gitlab_ci_local_parser.py
ci_test/job_rules.py
ci_test/main.py
ci_test/rule_collator.py
ci_test/rule_formatter.py
ci_test_toolkit-0.0.1.dist-info/LICENSE
ci_test_toolkit-0.0.1.dist-info/METADATA
ci_test_toolkit-0.0.1.dist-info/WHEEL
ci_test_toolkit-0.0.1.dist-info/entry_points.txt
ci_test_toolkit-0.0.1.dist-info/top_level.txt
ci_test_toolkit-0.0.1.dist-info/RECORD
